{"id":"00000000-0000-0000-0000-000000000000","revision":0,"last_node_id":92,"last_link_id":152,"nodes":[{"id":38,"type":"CompareSMPLtoBVH","pos":[10980,3370],"size":[420,580],"flags":{},"order":28,"mode":4,"inputs":[{"localized_name":"smpl_params","name":"smpl_params","type":"SMPL_PARAMS","link":32},{"localized_name":"bvh_data","name":"bvh_data","type":"BVH_DATA","link":31}],"outputs":[{"localized_name":"info","name":"info","type":"STRING","links":null}],"properties":{"cnr_id":"comfyui-motioncapture","ver":"dcd220c706a7d4c54a6ab37db21acbd3eea2394f","Node name for S&R":"CompareSMPLtoBVH"},"widgets_values":[""]},{"id":13,"type":"LoadGVHMRModels","pos":[10660,3260],"size":[270,60],"flags":{},"order":0,"mode":4,"inputs":[{"localized_name":"model_path_override","name":"model_path_override","shape":7,"type":"STRING","widget":{"name":"model_path_override"},"link":null}],"outputs":[{"localized_name":"model","name":"model","type":"GVHMR_MODEL","links":[5]}],"properties":{"cnr_id":"comfyui-motioncapture","ver":"0a313b6cbd87f105051ef640ca981340f3b76587","Node name for S&R":"LoadGVHMRModels","aux_id":"PozzettiAndrea/ComfyUI-MotionCapture"},"widgets_values":[""]},{"id":5,"type":"LoadSMPL","pos":[10980,2890],"size":[270,150],"flags":{},"order":1,"mode":4,"inputs":[{"localized_name":"npz_file","name":"npz_file","type":"COMBO","widget":{"name":"npz_file"},"link":null},{"localized_name":"source_folder","name":"source_folder","type":"COMBO","widget":{"name":"source_folder"},"link":null}],"outputs":[{"localized_name":"smpl_params","name":"smpl_params","type":"SMPL_PARAMS","links":[]},{"localized_name":"info","name":"info","type":"STRING","links":null}],"properties":{"cnr_id":"comfyui-motioncapture","ver":"dcd220c706a7d4c54a6ab37db21acbd3eea2394f","Node name for S&R":"LoadSMPL"},"widgets_values":["mhr_motion.npz",false,"refresh","output"]},{"id":16,"type":"LoadSAM3DBodyModels","pos":[10660,4570],"size":[276.740234375,82],"flags":{},"order":2,"mode":4,"inputs":[{"localized_name":"model_path_override","name":"model_path_override","shape":7,"type":"STRING","widget":{"name":"model_path_override"},"link":null},{"localized_name":"hf_token","name":"hf_token","shape":7,"type":"STRING","widget":{"name":"hf_token"},"link":null}],"outputs":[{"localized_name":"model","name":"model","type":"SAM3D_MODEL","links":[7]}],"properties":{"cnr_id":"comfyui-motioncapture","ver":"a0a52dedb2657d6a8d7a82063d20085dd807143a","Node name for S&R":"LoadSAM3DBodyModels"},"widgets_values":["I:\\ComfyUI_Models\\sam-3d-body",""]},{"id":18,"type":"SaveMHR","pos":[10660,4950],"size":[270,78],"flags":{},"order":24,"mode":4,"inputs":[{"localized_name":"mhr_params","name":"mhr_params","type":"MHR_PARAMS","link":8},{"localized_name":"output_path","name":"output_path","type":"STRING","widget":{"name":"output_path"},"link":null}],"outputs":[{"localized_name":"file_path","name":"file_path","type":"STRING","links":[]},{"localized_name":"info","name":"info","type":"STRING","links":null}],"properties":{"cnr_id":"comfyui-motioncapture","ver":"a0a52dedb2657d6a8d7a82063d20085dd807143a","Node name for S&R":"SaveMHR"},"widgets_values":["output/mhr_motion.npz"]},{"id":20,"type":"SaveSMPL","pos":[10660,3570],"size":[270,78],"flags":{},"order":22,"mode":4,"inputs":[{"localized_name":"smpl_params","name":"smpl_params","type":"SMPL_PARAMS","link":12},{"localized_name":"output_path","name":"output_path","type":"STRING","widget":{"name":"output_path"},"link":null}],"outputs":[{"localized_name":"file_path","name":"file_path","type":"STRING","links":null},{"localized_name":"info","name":"info","type":"STRING","links":null}],"properties":{"cnr_id":"comfyui-motioncapture","ver":"c8a7572bbce6990005e1375b478d0a12d3ae7bab","Node name for S&R":"SaveSMPL","aux_id":"PozzettiAndrea/ComfyUI-MotionCapture"},"widgets_values":["output/taichi.npz"]},{"id":25,"type":"SMPLtoBVH","pos":[10660,3700],"size":[270,146],"flags":{},"order":23,"mode":4,"inputs":[{"localized_name":"smpl_params","name":"smpl_params","type":"SMPL_PARAMS","link":23},{"localized_name":"output_path","name":"output_path","type":"STRING","widget":{"name":"output_path"},"link":null},{"localized_name":"fps","name":"fps","type":"INT","widget":{"name":"fps"},"link":null},{"localized_name":"scale","name":"scale","type":"FLOAT","widget":{"name":"scale"},"link":null}],"outputs":[{"localized_name":"bvh_data","name":"bvh_data","type":"BVH_DATA","links":[31]},{"localized_name":"file_path","name":"file_path","type":"STRING","links":null},{"localized_name":"info","name":"info","type":"STRING","links":null}],"properties":{"cnr_id":"comfyui-motioncapture","ver":"dcd220c706a7d4c54a6ab37db21acbd3eea2394f","Node name for S&R":"SMPLtoBVH"},"widgets_values":["output/taichi.bvh",25,1]},{"id":44,"type":"SAM3DBodyPreviewRiggedMesh","pos":[11700,5480],"size":[512,798],"flags":{},"order":21,"mode":4,"inputs":[{"localized_name":"fbx_output_path","name":"fbx_output_path","type":"STRING","widget":{"name":"fbx_output_path"},"link":43}],"outputs":[],"properties":{"cnr_id":"ComfyUI-SAM3DBody","ver":"e84b3445ce4879dbe66d5d60fe2be7a29f6f9518","Node name for S&R":"SAM3DBodyPreviewRiggedMesh","aux_id":"PozzettiAndrea/ComfyUI-SAM3DBody"},"widgets_values":["I:\\ComfyUI_Motion\\ComfyUI\\output\\sam3d_rigged.fbx",""]},{"id":17,"type":"SAM3DVideoInference","pos":[10660,4700],"size":[272.7265625,194],"flags":{},"order":19,"mode":4,"inputs":[{"localized_name":"images","name":"images","type":"IMAGE","link":34},{"localized_name":"masks","name":"masks","type":"MASK","link":11},{"localized_name":"model","name":"model","type":"SAM3D_MODEL","link":7},{"localized_name":"inference_type","name":"inference_type","shape":7,"type":"COMBO","widget":{"name":"inference_type"},"link":null},{"localized_name":"temporal_smoothing","name":"temporal_smoothing","shape":7,"type":"BOOLEAN","widget":{"name":"temporal_smoothing"},"link":null},{"localized_name":"smoothing_sigma","name":"smoothing_sigma","shape":7,"type":"FLOAT","widget":{"name":"smoothing_sigma"},"link":null},{"localized_name":"smoothing_method","name":"smoothing_method","shape":7,"type":"COMBO","widget":{"name":"smoothing_method"},"link":null},{"localized_name":"bbox_scale","name":"bbox_scale","shape":7,"type":"FLOAT","widget":{"name":"bbox_scale"},"link":null}],"outputs":[{"localized_name":"mhr_params","name":"mhr_params","type":"MHR_PARAMS","links":[8,25]},{"localized_name":"visualization","name":"visualization","type":"IMAGE","links":[]},{"localized_name":"info","name":"info","type":"STRING","links":[]}],"properties":{"cnr_id":"comfyui-motioncapture","ver":"a0a52dedb2657d6a8d7a82063d20085dd807143a","Node name for S&R":"SAM3DVideoInference"},"widgets_values":["full",true,3,"gaussian",1.2]},{"id":46,"type":"SAM3DBodyExportFBX","pos":[11380,5480],"size":[270,58],"flags":{},"order":16,"mode":4,"inputs":[{"localized_name":"mesh_data","name":"mesh_data","type":"SAM3D_OUTPUT","link":53},{"localized_name":"output_filename","name":"output_filename","type":"STRING","widget":{"name":"output_filename"},"link":null}],"outputs":[{"localized_name":"fbx_path","name":"fbx_path","type":"STRING","links":[43]}],"properties":{"cnr_id":"ComfyUI-SAM3DBody","ver":"e84b3445ce4879dbe66d5d60fe2be7a29f6f9518","Node name for S&R":"SAM3DBodyExportFBX","aux_id":"PozzettiAndrea/ComfyUI-SAM3DBody"},"widgets_values":["sam3d_rigged1.fbx"]},{"id":50,"type":"SAM3DBodySaveSkeleton","pos":[11380,5580],"size":[270,82],"flags":{},"order":17,"mode":4,"inputs":[{"localized_name":"skeleton","name":"skeleton","type":"SKELETON","link":54},{"localized_name":"output_filename","name":"output_filename","type":"STRING","widget":{"name":"output_filename"},"link":null},{"localized_name":"format","name":"format","type":"COMBO","widget":{"name":"format"},"link":null}],"outputs":[{"localized_name":"filepath","name":"filepath","type":"STRING","links":null}],"properties":{"cnr_id":"ComfyUI-SAM3DBody","ver":"058315cfd490d45278e606a319a8848a04c6496a","Node name for S&R":"SAM3DBodySaveSkeleton"},"widgets_values":["skeleton1","bvh"]},{"id":45,"type":"LoadSAM3DBodyModel","pos":[10660,5480],"size":[273.7994140625,58],"flags":{},"order":3,"mode":4,"inputs":[{"localized_name":"model_path","name":"model_path","type":"STRING","widget":{"name":"model_path"},"link":null}],"outputs":[{"localized_name":"model","name":"model","type":"SAM3D_MODEL","links":[36,46]}],"properties":{"cnr_id":"ComfyUI-SAM3DBody","ver":"5fef822c291d4a440e8392acdc40fa3d93a0820d","Node name for S&R":"LoadSAM3DBodyModel"},"widgets_values":["I:\\ComfyUI_Models\\sam-3d-body"]},{"id":19,"type":"MHRViewer","pos":[10980,4570],"size":[400,770],"flags":{},"order":25,"mode":4,"inputs":[{"localized_name":"mhr_params","name":"mhr_params","shape":7,"type":"MHR_PARAMS","link":25},{"localized_name":"npz_path","name":"npz_path","shape":7,"type":"STRING","widget":{"name":"npz_path"},"link":null},{"localized_name":"frame_skip","name":"frame_skip","shape":7,"type":"INT","widget":{"name":"frame_skip"},"link":null},{"localized_name":"joint_size","name":"joint_size","shape":7,"type":"FLOAT","widget":{"name":"joint_size"},"link":null},{"localized_name":"bone_width","name":"bone_width","shape":7,"type":"FLOAT","widget":{"name":"bone_width"},"link":null},{"localized_name":"show_hands","name":"show_hands","shape":7,"type":"BOOLEAN","widget":{"name":"show_hands"},"link":null}],"outputs":[{"localized_name":"viewer_data","name":"viewer_data","type":"MHR_VIEWER","links":null}],"properties":{"cnr_id":"comfyui-motioncapture","ver":"a0a52dedb2657d6a8d7a82063d20085dd807143a","Node name for S&R":"MHRViewer"},"widgets_values":["I:\\ComfyUI_Motion\\ComfyUI\\output\\mhr_motion.npz",1,5,2,true,""]},{"id":12,"type":"ImageToMask","pos":[10280,3950],"size":[260,58],"flags":{},"order":15,"mode":0,"inputs":[{"localized_name":"image","name":"image","type":"IMAGE","link":35},{"localized_name":"channel","name":"channel","type":"COMBO","widget":{"name":"channel"},"link":null}],"outputs":[{"localized_name":"MASK","name":"MASK","type":"MASK","links":[4,11,143]}],"properties":{"cnr_id":"comfy-core","ver":"0.3.71","Node name for S&R":"ImageToMask"},"widgets_values":["red"]},{"id":68,"type":"PreviewAny","pos":[10980,4200],"size":[210,166],"flags":{},"order":26,"mode":4,"inputs":[{"localized_name":"source","name":"source","type":"*","link":144}],"outputs":[],"properties":{"cnr_id":"comfy-core","ver":"0.9.2","Node name for S&R":"PreviewAny"},"widgets_values":[null,null,null]},{"id":52,"type":"SAM3DBodyProcessAdvanced","pos":[10990,5640],"size":[350,290],"flags":{},"order":14,"mode":4,"inputs":[{"localized_name":"model","name":"model","type":"SAM3D_MODEL","link":46},{"localized_name":"image","name":"image","type":"IMAGE","link":151},{"localized_name":"mask","name":"mask","shape":7,"type":"MASK","link":152},{"localized_name":"bbox_threshold","name":"bbox_threshold","type":"FLOAT","widget":{"name":"bbox_threshold"},"link":null},{"localized_name":"nms_threshold","name":"nms_threshold","type":"FLOAT","widget":{"name":"nms_threshold"},"link":null},{"localized_name":"inference_type","name":"inference_type","type":"COMBO","widget":{"name":"inference_type"},"link":null},{"localized_name":"detector_name","name":"detector_name","type":"COMBO","widget":{"name":"detector_name"},"link":null},{"localized_name":"segmentor_name","name":"segmentor_name","type":"COMBO","widget":{"name":"segmentor_name"},"link":null},{"localized_name":"fov_name","name":"fov_name","type":"COMBO","widget":{"name":"fov_name"},"link":null},{"localized_name":"detector_path","name":"detector_path","shape":7,"type":"STRING","widget":{"name":"detector_path"},"link":null},{"localized_name":"segmentor_path","name":"segmentor_path","shape":7,"type":"STRING","widget":{"name":"segmentor_path"},"link":null},{"localized_name":"fov_path","name":"fov_path","shape":7,"type":"STRING","widget":{"name":"fov_path"},"link":null}],"outputs":[{"localized_name":"mesh_data","name":"mesh_data","type":"SAM3D_OUTPUT","links":[]},{"localized_name":"skeleton","name":"skeleton","type":"SKELETON","links":[]},{"localized_name":"debug_image","name":"debug_image","type":"IMAGE","links":null}],"properties":{"cnr_id":"ComfyUI-SAM3DBody","ver":"058315cfd490d45278e606a319a8848a04c6496a","Node name for S&R":"SAM3DBodyProcessAdvanced"},"widgets_values":[0.8,0.3,"full","vitdet","sam2","moge2","","",""]},{"id":77,"type":"LoadImage","pos":[10660,5590],"size":[282.8249969482422,314.00000000000045],"flags":{},"order":4,"mode":4,"inputs":[{"localized_name":"image","name":"image","type":"COMBO","widget":{"name":"image"},"link":null},{"localized_name":"choose file to upload","name":"upload","type":"IMAGEUPLOAD","widget":{"name":"upload"},"link":null}],"outputs":[{"localized_name":"IMAGE","name":"IMAGE","type":"IMAGE","links":[149,151]},{"localized_name":"MASK","name":"MASK","type":"MASK","links":[150,152]}],"properties":{"cnr_id":"comfy-core","ver":"0.9.2","Node name for S&R":"LoadImage"},"widgets_values":["masked_dancing.png","image"]},{"id":43,"type":"SAM3DBodyProcess","pos":[10990,5480],"size":[350,122],"flags":{},"order":13,"mode":4,"inputs":[{"localized_name":"model","name":"model","type":"SAM3D_MODEL","link":36},{"localized_name":"image","name":"image","type":"IMAGE","link":149},{"localized_name":"mask","name":"mask","shape":7,"type":"MASK","link":150},{"localized_name":"bbox_threshold","name":"bbox_threshold","type":"FLOAT","widget":{"name":"bbox_threshold"},"link":null},{"localized_name":"inference_type","name":"inference_type","type":"COMBO","widget":{"name":"inference_type"},"link":null}],"outputs":[{"localized_name":"mesh_data","name":"mesh_data","type":"SAM3D_OUTPUT","links":[53]},{"localized_name":"skeleton","name":"skeleton","type":"SKELETON","links":[54]},{"localized_name":"debug_image","name":"debug_image","type":"IMAGE","links":[]}],"properties":{"cnr_id":"ComfyUI-SAM3DBody","ver":"e84b3445ce4879dbe66d5d60fe2be7a29f6f9518","Node name for S&R":"SAM3DBodyProcess","aux_id":"PozzettiAndrea/ComfyUI-SAM3DBody"},"widgets_values":[0.8,"full"]},{"id":14,"type":"GVHMRInference","pos":[10660,3370],"size":[270,146],"flags":{},"order":18,"mode":4,"inputs":[{"localized_name":"images","name":"images","type":"IMAGE","link":33},{"localized_name":"masks","name":"masks","type":"MASK","link":4},{"localized_name":"model","name":"model","type":"GVHMR_MODEL","link":5},{"localized_name":"static_camera","name":"static_camera","type":"BOOLEAN","widget":{"name":"static_camera"},"link":null},{"localized_name":"focal_length_mm","name":"focal_length_mm","shape":7,"type":"INT","widget":{"name":"focal_length_mm"},"link":null},{"localized_name":"bbox_scale","name":"bbox_scale","shape":7,"type":"FLOAT","widget":{"name":"bbox_scale"},"link":null}],"outputs":[{"localized_name":"smpl_params","name":"smpl_params","type":"SMPL_PARAMS","links":[12,23,32]},{"localized_name":"visualization","name":"visualization","type":"IMAGE","links":[]},{"localized_name":"info","name":"info","type":"STRING","links":null}],"properties":{"cnr_id":"comfyui-motioncapture","ver":"0a313b6cbd87f105051ef640ca981340f3b76587","Node name for S&R":"GVHMRInference","aux_id":"PozzettiAndrea/ComfyUI-MotionCapture"},"widgets_values":[true,0,1.2]},{"id":86,"type":"SAM3D From Video JK","pos":[10660,4200],"size":[280,194],"flags":{},"order":20,"mode":4,"inputs":[{"localized_name":"model","name":"model","type":"SAM3D_MODEL","link":141},{"localized_name":"image","name":"image","type":"IMAGE","link":142},{"localized_name":"mask","name":"mask","shape":7,"type":"MASK","link":143},{"localized_name":"output_filename","name":"output_filename","type":"STRING","widget":{"name":"output_filename"},"link":null},{"localized_name":"bbox_threshold","name":"bbox_threshold","shape":7,"type":"FLOAT","widget":{"name":"bbox_threshold"},"link":null},{"localized_name":"inference_type","name":"inference_type","shape":7,"type":"COMBO","widget":{"name":"inference_type"},"link":null},{"localized_name":"smoothing_method","name":"smoothing_method","shape":7,"type":"COMBO","widget":{"name":"smoothing_method"},"link":null},{"localized_name":"smoothing_sigma","name":"smoothing_sigma","shape":7,"type":"FLOAT","widget":{"name":"smoothing_sigma"},"link":null}],"outputs":[{"localized_name":"bin_file_path","name":"bin_file_path","type":"STRING","links":[144,145]}],"properties":{"cnr_id":"comfyui-jakeupgrade","ver":"e6299ea1433d41f0f78d60a2e7aeb3ae2776d9e8","Node name for S&R":"SAM3D From Video JK"},"widgets_values":["mesh_sequence",0.8,"full","gaussian",2]},{"id":41,"type":"VHS_LoadVideoPath","pos":[10280,3370],"size":[260,540],"flags":{},"order":6,"mode":0,"inputs":[{"localized_name":"meta_batch","name":"meta_batch","shape":7,"type":"VHS_BatchManager","link":null},{"localized_name":"vae","name":"vae","shape":7,"type":"VAE","link":null},{"localized_name":"video","name":"video","type":"STRING","widget":{"name":"video"},"link":null},{"localized_name":"force_rate","name":"force_rate","type":"FLOAT","widget":{"name":"force_rate"},"link":null},{"localized_name":"custom_width","name":"custom_width","type":"INT","widget":{"name":"custom_width"},"link":null},{"localized_name":"custom_height","name":"custom_height","type":"INT","widget":{"name":"custom_height"},"link":null},{"localized_name":"frame_load_cap","name":"frame_load_cap","type":"INT","widget":{"name":"frame_load_cap"},"link":null},{"localized_name":"skip_first_frames","name":"skip_first_frames","type":"INT","widget":{"name":"skip_first_frames"},"link":null},{"localized_name":"select_every_nth","name":"select_every_nth","type":"INT","widget":{"name":"select_every_nth"},"link":null},{"localized_name":"format","name":"format","shape":7,"type":"COMBO","widget":{"name":"format"},"link":null}],"outputs":[{"localized_name":"IMAGE","name":"IMAGE","type":"IMAGE","links":[33,34,142]},{"localized_name":"frame_count","name":"frame_count","type":"INT","links":null},{"localized_name":"audio","name":"audio","type":"AUDIO","links":null},{"localized_name":"video_info","name":"video_info","type":"VHS_VIDEOINFO","links":null}],"properties":{"cnr_id":"comfyui-videohelpersuite","ver":"993082e4f2473bf4acaf06f51e33877a7eb38960","Node name for S&R":"VHS_LoadVideoPath"},"widgets_values":{"video":"\"I:\\ComfyUI_Video\\ComfyUI\\input\\taichi.mp4\"","force_rate":0,"custom_width":0,"custom_height":0,"frame_load_cap":0,"skip_first_frames":0,"select_every_nth":1,"format":"Wan","videopreview":{"hidden":false,"paused":false,"params":{"filename":"\"I:\\ComfyUI_Video\\ComfyUI\\input\\taichi.mp4\"","type":"path","format":"video/mp4\"","force_rate":0,"custom_width":0,"custom_height":0,"frame_load_cap":0,"skip_first_frames":0,"select_every_nth":1}}}},{"id":30,"type":"Adv3DViewer_JK","pos":[11450,4180],"size":[980,710],"flags":{},"order":27,"mode":0,"inputs":[{"localized_name":"file_path","name":"file_path","shape":7,"type":"STRING","widget":{"name":"file_path"},"link":145}],"outputs":[{"localized_name":"info","name":"info","type":"STRING","links":null}],"properties":{"cnr_id":"comfyui-jakeupgrade","ver":"c4390f5caf2f9de73fc40153c17d990d91f00217","Node name for S&R":"Adv3DViewer_JK"},"widgets_values":["",""]},{"id":88,"type":"Note","pos":[10660,5080],"size":[210,88],"flags":{},"order":7,"mode":4,"inputs":[],"outputs":[],"title":"restriction","properties":{},"widgets_values":["1. upside-down\n2. (0, 0, 0) constraint\n3. not ready to use"],"color":"#432","bgcolor":"#653"},{"id":40,"type":"LoadBVHFromFolder","pos":[10980,3090],"size":[270,58],"flags":{},"order":8,"mode":4,"inputs":[{"localized_name":"bvh_file","name":"bvh_file","type":"COMBO","widget":{"name":"bvh_file"},"link":null}],"outputs":[{"localized_name":"bvh_data","name":"bvh_data","type":"BVH_DATA","links":[]}],"properties":{"cnr_id":"comfyui-motioncapture","ver":"dcd220c706a7d4c54a6ab37db21acbd3eea2394f","Node name for S&R":"LoadBVHFromFolder"},"widgets_values":["output/motion.bvh"]},{"id":67,"type":"LoadSAM3DBodyModel","pos":[10660,4100],"size":[280,60],"flags":{},"order":9,"mode":4,"inputs":[{"localized_name":"model_path","name":"model_path","type":"STRING","widget":{"name":"model_path"},"link":null}],"outputs":[{"localized_name":"model","name":"model","type":"SAM3D_MODEL","links":[141]}],"properties":{"cnr_id":"ComfyUI-SAM3DBody","ver":"5fef822c291d4a440e8392acdc40fa3d93a0820d","Node name for S&R":"LoadSAM3DBodyModel"},"widgets_values":["I:\\ComfyUI_Models\\sam-3d-body"]},{"id":90,"type":"MarkdownNote","pos":[11450,4040],"size":[510,88],"flags":{},"order":10,"mode":0,"inputs":[],"outputs":[],"title":"Video Instructions","properties":{},"widgets_values":["[ComfyUI WanVideo update5: Long vid gen with Camera Control & Pose Control](https://youtu.be/yO7bun8wN3o)  \n[ComfyUI WanVideo update5.1: uses SAM3D Body to generate character motion model sequences](https://youtu.be/OJNodd1hYCs)"],"color":"#432","bgcolor":"#653"},{"id":89,"type":"Note","pos":[10980,3240],"size":[420,88],"flags":{},"order":11,"mode":4,"inputs":[],"outputs":[],"properties":{},"widgets_values":["copy the file path of the smpl_xxx.bin(mesh sequence cache) in the output subfolder of your ComfyUI (for Motion) floder, generated by the Compare SMPL vs BVH node. Then open using the Adv 3D Viewer node."],"color":"#432","bgcolor":"#653"},{"id":92,"type":"MarkdownNote","pos":[10000,4060],"size":[260,88],"flags":{},"order":12,"mode":0,"inputs":[],"outputs":[],"title":"How to gen Mask Video","properties":{},"widgets_values":["Try JK_module_Video-AutoMask workflow, using:  \n[SAM2](https://github.com/kijai/ComfyUI-segment-anything-2)  \n[SAM3](https://github.com/PozzettiAndrea/ComfyUI-SAM3)  \n[Mat Anyone](https://github.com/KytraScript/ComfyUI_MatAnyone_Kytra)"],"color":"#432","bgcolor":"#653"},{"id":42,"type":"VHS_LoadVideoPath","pos":[10280,4060],"size":[260,540],"flags":{},"order":5,"mode":0,"inputs":[{"localized_name":"meta_batch","name":"meta_batch","shape":7,"type":"VHS_BatchManager","link":null},{"localized_name":"vae","name":"vae","shape":7,"type":"VAE","link":null},{"localized_name":"video","name":"video","type":"STRING","widget":{"name":"video"},"link":null},{"localized_name":"force_rate","name":"force_rate","type":"FLOAT","widget":{"name":"force_rate"},"link":null},{"localized_name":"custom_width","name":"custom_width","type":"INT","widget":{"name":"custom_width"},"link":null},{"localized_name":"custom_height","name":"custom_height","type":"INT","widget":{"name":"custom_height"},"link":null},{"localized_name":"frame_load_cap","name":"frame_load_cap","type":"INT","widget":{"name":"frame_load_cap"},"link":null},{"localized_name":"skip_first_frames","name":"skip_first_frames","type":"INT","widget":{"name":"skip_first_frames"},"link":null},{"localized_name":"select_every_nth","name":"select_every_nth","type":"INT","widget":{"name":"select_every_nth"},"link":null},{"localized_name":"format","name":"format","shape":7,"type":"COMBO","widget":{"name":"format"},"link":null}],"outputs":[{"localized_name":"IMAGE","name":"IMAGE","type":"IMAGE","links":[35]},{"localized_name":"frame_count","name":"frame_count","type":"INT","links":null},{"localized_name":"audio","name":"audio","type":"AUDIO","links":null},{"localized_name":"video_info","name":"video_info","type":"VHS_VIDEOINFO","links":null}],"properties":{"cnr_id":"comfyui-videohelpersuite","ver":"993082e4f2473bf4acaf06f51e33877a7eb38960","Node name for S&R":"VHS_LoadVideoPath"},"widgets_values":{"video":"\"I:\\ComfyUI_Video\\ComfyUI\\input\\taichi_m.mp4\"","force_rate":0,"custom_width":0,"custom_height":0,"frame_load_cap":0,"skip_first_frames":0,"select_every_nth":1,"format":"Wan","videopreview":{"hidden":false,"paused":false,"params":{"filename":"\"I:\\ComfyUI_Video\\ComfyUI\\input\\taichi_m.mp4\"","type":"path","format":"video/mp4\"","force_rate":0,"custom_width":0,"custom_height":0,"frame_load_cap":0,"skip_first_frames":0,"select_every_nth":1}}}}],"links":[[4,12,0,14,1,"MASK"],[5,13,0,14,2,"GVHMR_MODEL"],[7,16,0,17,2,"SAM3D_MODEL"],[8,17,0,18,0,"MHR_PARAMS"],[11,12,0,17,1,"MASK"],[12,14,0,20,0,"SMPL_PARAMS"],[23,14,0,25,0,"SMPL_PARAMS"],[25,17,0,19,0,"MHR_PARAMS"],[31,25,0,38,1,"BVH_DATA"],[32,14,0,38,0,"SMPL_PARAMS"],[33,41,0,14,0,"IMAGE"],[34,41,0,17,0,"IMAGE"],[35,42,0,12,0,"IMAGE"],[36,45,0,43,0,"SAM3D_MODEL"],[43,46,0,44,0,"STRING"],[46,45,0,52,0,"SAM3D_MODEL"],[53,43,0,46,0,"SAM3D_OUTPUT"],[54,43,1,50,0,"SKELETON"],[141,67,0,86,0,"SAM3D_MODEL"],[142,41,0,86,1,"IMAGE"],[143,12,0,86,2,"MASK"],[144,86,0,68,0,"STRING"],[145,86,0,30,0,"STRING"],[149,77,0,43,1,"IMAGE"],[150,77,1,43,2,"MASK"],[151,77,0,52,1,"IMAGE"],[152,77,1,52,2,"MASK"]],"groups":[{"id":1,"title":"mesh sequence + skeleton animation - SMPL","bounding":[10650,3170,760,793.6],"color":"#3f789e","font_size":24,"flags":{}},{"id":2,"title":"skeleton animation - SAM3D Body","bounding":[10650,4500,740,853.6],"color":"#3f789e","font_size":24,"flags":{}},{"id":3,"title":"single mesh + skeleton - SAM3D Body","bounding":[10650,5410,1572,897.6],"color":"#3f789e","font_size":24,"flags":{}},{"id":4,"title":"mesh sequence - SAM3D Body","bounding":[10650,4030,560,377.6],"color":"#3f789e","font_size":24,"flags":{}}],"config":{},"extra":{"ds":{"scale":0.4736244074476928,"offset":[-9291.808643407749,-2737.0351855917934]},"workflowRendererVersion":"LG"},"version":0.4}